{
  "article_number": 119,
  "title": "ุงููุตู 119",
  "document_name": "ูุฌูุฉ ุงูุทุฑูุงุช",
  "page_title": "ูุฌูุฉ ุงูุทุฑูุงุช - ุงููุตู 119 - ูุงููู ๐น๐ณ",
  "description": "ูุง ุชููุน ุฃุญูุงู ูุฐู ุงููุฌูุฉ ุงูุณูุทุงุช ุงูุจูุฏูุฉ ูู ุงุชุฎุงุฐ ุชุฏุงุจูุฑ ุฃุดุฏ ุตุฑุงูุฉ ูู ุงูุชุฏุงุจูุฑ ุงููุงุฑุฏุฉ ุจูุฐู ุงููุฌูุฉ ูุฐูู ูู ุญุฏูุฏ ูุง ููุง ูู ุงููููุฐ ููููุง...",
  "keywords": null,
  "content": {
    "full_text": "ูุง ุชููุน ุฃุญูุงู ูุฐู ุงููุฌูุฉ ุงูุณูุทุงุช ุงูุจูุฏูุฉ ูู ุงุชุฎุงุฐ ุชุฏุงุจูุฑ ุฃุดุฏ ุตุฑุงูุฉ ูู ุงูุชุฏุงุจูุฑ ุงููุงุฑุฏุฉ ุจูุฐู ุงููุฌูุฉ ูุฐูู ูู ุญุฏูุฏ ูุง ููุง ูู ุงููููุฐ ููููุง ุงูุชุถุช ุฐูู ูุตูุญุฉ ุงูุฃูู ุฃู ุงููุธุงู ุงูุนุงู. ููุง ุชููู ุงููุฑุงุฑุงุช ุงูุชู ุชุชุฎุฐูุง ุงูุณูุทุงุช ุงูุจูุฏูุฉ ุชุทุจููุง ููุฐุง ุงููุตู ููุชูููุฐ ุฅูุง ุจุนุฏ ุงูุชุฃุดูุฑ ุนูููุง ูู ูุจู ุงูููุงุฉ.",
    "length": 282,
    "word_count": 50,
    "paragraphs": [
      "ูุง ุชููุน ุฃุญูุงู ูุฐู ุงููุฌูุฉ ุงูุณูุทุงุช ุงูุจูุฏูุฉ ูู ุงุชุฎุงุฐ ุชุฏุงุจูุฑ ุฃุดุฏ ุตุฑุงูุฉ ูู ุงูุชุฏุงุจูุฑ ุงููุงุฑุฏุฉ ุจูุฐู ุงููุฌูุฉ ูุฐูู ูู ุญุฏูุฏ ูุง ููุง ูู ุงููููุฐ ููููุง ุงูุชุถุช ุฐูู ูุตูุญุฉ ุงูุฃูู ุฃู ุงููุธุงู ุงูุนุงู. ููุง ุชููู ุงููุฑุงุฑุงุช ุงูุชู ุชุชุฎุฐูุง ุงูุณูุทุงุช ุงูุจูุฏูุฉ ุชุทุจููุง ููุฐุง ุงููุตู ููุชูููุฐ ุฅูุง ุจุนุฏ ุงูุชุฃุดูุฑ ุนูููุง ูู ูุจู ุงูููุงุฉ."
    ],
    "paragraph_count": 1,
    "numbered_items": []
  },
  "definitions": null,
  "definition_count": 0,
  "structure": {
    "has_structured_data": false,
    "has_amendments": false,
    "has_references": false,
    "referenced_articles": []
  },
  "educational_content": null,
  "learning_metadata": {
    "difficulty_level": "intermediate",
    "estimated_study_time_minutes": 5,
    "content_type": "regulations",
    "requires_visual_aids": false,
    "suitable_for_video": false
  },
  "metadata": {
    "url": "https://9anoun.tn/kb/codes/code-route/code-route-article-119",
    "scraped_at": "2026-02-01T15:59:29.319125",
    "language": "ar",
    "source": "https://9anoun.tn"
  }
}